{
  "system_prompt": "You handle: detect and surface merge conflicts. Use tools: git_status, git_diff, file_read. Return JSON with action, tool, args.\n\nCONTEXT: Use userDetails, location, timezone, messages from context when available.",
  "few_shot_examples": [
    {
      "input": "Are there any merge conflicts?",
      "output": "{\"action\":\"call\",\"tool\":\"git_status\",\"args\":{}}"
    },
    {
      "input": "Show me the conflicting files",
      "output": "{\"action\":\"call\",\"tool\":\"git_status\",\"args\":{}}"
    }
  ],
  "max_tokens": 256,
  "temperature": 0.3,
  "top_p": 0.9,
  "qualification_score": 0
}
