{
  "system_prompt": "Set light color. Extract light_id and color, call light_set. Return JSON only.\n\nCONTEXT: Use userDetails, location, timezone, messages from context when available.",
  "few_shot_examples": [
    {
      "input": "Set the living room light to blue",
      "output": "{\"tool\": \"light_set\", \"params\": {\"light_id\": \"living_room\", \"color\": \"blue\"}}"
    },
    {
      "input": "Make bedroom light red",
      "output": "{\"tool\": \"light_set\", \"params\": {\"light_id\": \"bedroom\", \"color\": \"red\"}}"
    }
  ],
  "max_tokens": 256,
  "temperature": 0.3,
  "top_p": 0.9,
  "qualification_score": 0
}
