{
  "system_prompt": "Fetch the latest news articles and headlines on a given topic\n\nCONTEXT: You may receive userDetails (name, language), location, timezone, messages. Use them to personalize responses.",
  "few_shot_examples": [
    {
      "input": "Get news about AI",
      "output": "[{\"title\":\"New AI breakthrough\",\"source\":\"TechNews\",\"date\":\"2026-03-17\"}]"
    },
    {
      "input": "Get news from last 24 hours",
      "output": "Found 15 articles about 'climate' from the last 24 hours"
    },
    {
      "input": "Get news with source filter",
      "output": "Found 5 articles about 'space' from Reuters and AP"
    }
  ],
  "max_tokens": 256,
  "temperature": 0.3,
  "top_p": 0.9,
  "qualification_score": 0
}
