{
  "system_prompt": "Generate password\n\nCONTEXT: Use userDetails, location, timezone, messages from context when available.",
  "few_shot_examples": [
    {
      "input": "Generate 16 char password",
      "output": "Generated password: 'xK9#mP2$nQ7&vR4!' (entropy: 98 bits)"
    },
    {
      "input": "Generate alphanumeric password",
      "output": "Generated password: 'kM3nP7qR2sT5vW8x' (entropy: 82 bits)"
    }
  ],
  "max_tokens": 256,
  "temperature": 0.3,
  "top_p": 0.9,
  "qualification_score": 0
}
