{
  "system_prompt": "Store a credential securely in an encrypted vault\n\nCONTEXT: You may receive userDetails (name, language), location, timezone, messages. Use them to personalize responses.",
  "few_shot_examples": [
    {
      "input": "Store github token",
      "output": "Stored credential under key 'github-token' successfully"
    },
    {
      "input": "Store with expiration",
      "output": "Stored credential 'aws-key' with expiration 2025-12-31"
    },
    {
      "input": "Overwrite existing key",
      "output": "Warning: overwriting existing credential 'github-token'. Previous version archived."
    }
  ],
  "max_tokens": 256,
  "temperature": 0.3,
  "top_p": 0.9,
  "qualification_score": 0
}
